kusto_query_language_parser/__init__.py
kusto_query_language_parser/grammar/Kql.g4
kusto_query_language_parser/grammar/KqlTokens.g4
kusto_query_language_parser/parse_tools/Kql.interp
kusto_query_language_parser/parse_tools/Kql.tokens
kusto_query_language_parser/parse_tools/KqlLexer.interp
kusto_query_language_parser/parse_tools/KqlLexer.py
kusto_query_language_parser/parse_tools/KqlLexer.tokens
kusto_query_language_parser/parse_tools/KqlListener.py
kusto_query_language_parser/parse_tools/KqlParser.py
kusto_query_language_parser/parse_tools_v4.13/Kql.interp
kusto_query_language_parser/parse_tools_v4.13/Kql.tokens
kusto_query_language_parser/parse_tools_v4.13/KqlLexer.interp
kusto_query_language_parser/parse_tools_v4.13/KqlLexer.py
kusto_query_language_parser/parse_tools_v4.13/KqlLexer.tokens
kusto_query_language_parser/parse_tools_v4.13/KqlListener.py
kusto_query_language_parser/parse_tools_v4.13/KqlParser.py
kusto_query_language_parser/parse_tools_v4.13/KqlVisitor.py
kusto_query_language_parser/parser/kql_traverse.py
kusto_query_language_parser/parser/listener.py
kusto_query_language_parser-0.0.2.dist-info/METADATA
kusto_query_language_parser-0.0.2.dist-info/WHEEL
kusto_query_language_parser-0.0.2.dist-info/licenses/LICENSE
kusto_query_language_parser-0.0.2.dist-info/RECORD
